{
  "id": 5839,
  "chapter_id": 82,
  "verse_key": "82:10",
  "hizb_number": 59,
  "rub_el_hizb_number": 235,
  "ruku_number": 526,
  "manzil_number": 7,
  "page_number": 587,
  "juz_number": 30,
  "text_uthmani": "وَإِنَّ عَلَيْكُمْ لَحَـٰفِظِينَ",
  "audio_url": {
    "ahmedajamy": "https://cdn.islamic.network/quran/audio/128/ar.ahmedajamy/5839.mp3",
    "alafasy": "https://cdn.islamic.network/quran/audio/128/ar.alafasy/5839.mp3",
    "hudhaify": "https://cdn.islamic.network/quran/audio/128/ar.hudhaify/5839.mp3",
    "husary": "https://cdn.islamic.network/quran/audio/128/ar.husary/5839.mp3",
    "husarymujawwad": "https://cdn.islamic.network/quran/audio/128/ar.husarymujawwad/5839.mp3",
    "mahermuaiqly": "https://cdn.islamic.network/quran/audio/128/ar.mahermuaiqly/5839.mp3",
    "minshawi": "https://cdn.islamic.network/quran/audio/128/ar.minshawi/5839.mp3",
    "muhammadayyoub": "https://cdn.islamic.network/quran/audio/128/ar.muhammadayyoub/5839.mp3",
    "muhammadjibreel": "https://cdn.islamic.network/quran/audio/128/ar.muhammadjibreel/5839.mp3",
    "shaatree": "https://cdn.islamic.network/quran/audio/128/ar.shaatree/5839.mp3"
  },
  "words": [
    {
      "id": 11831,
      "line_number": 6,
      "audio_url": "https://audio.qurancdn.com/wbw/082_010_001.mp3",
      "text": "وَإِنَّ",
      "translation": "dan sesungguhnya",
      "transliteration": "wa-inna"
    },
    {
      "id": 11832,
      "line_number": 6,
      "audio_url": "https://audio.qurancdn.com/wbw/082_010_002.mp3",
      "text": "عَلَيْكُمْ",
      "translation": "atas kalian",
      "transliteration": "ʿalaykum"
    },
    {
      "id": 11833,
      "line_number": 6,
      "audio_url": "https://audio.qurancdn.com/wbw/082_010_003.mp3",
      "text": "لَحَـٰفِظِينَ",
      "translation": "sungguh ada penjaga",
      "transliteration": "laḥāfiẓīna"
    },
    {
      "id": 11834,
      "line_number": 6,
      "audio_url": null,
      "text": "١٠",
      "translation": "(10)",
      "transliteration": null
    }
  ],
  "translation": {
    "text": "Padahal sesungguhnya bagi kamu ada (malaikat-malaikat) yang mengawasi (pekerjaanmu),",
    "resource_name": "King Fahad Quran Complex"
  }
}