{
  "id": 5901,
  "chapter_id": 84,
  "verse_key": "84:17",
  "hizb_number": 59,
  "rub_el_hizb_number": 236,
  "ruku_number": 528,
  "manzil_number": 7,
  "page_number": 589,
  "juz_number": 30,
  "text_uthmani": "وَٱلَّيْلِ وَمَا وَسَقَ",
  "audio_url": {
    "ahmedajamy": "https://cdn.islamic.network/quran/audio/128/ar.ahmedajamy/5901.mp3",
    "alafasy": "https://cdn.islamic.network/quran/audio/128/ar.alafasy/5901.mp3",
    "hudhaify": "https://cdn.islamic.network/quran/audio/128/ar.hudhaify/5901.mp3",
    "husary": "https://cdn.islamic.network/quran/audio/128/ar.husary/5901.mp3",
    "husarymujawwad": "https://cdn.islamic.network/quran/audio/128/ar.husarymujawwad/5901.mp3",
    "mahermuaiqly": "https://cdn.islamic.network/quran/audio/128/ar.mahermuaiqly/5901.mp3",
    "minshawi": "https://cdn.islamic.network/quran/audio/128/ar.minshawi/5901.mp3",
    "muhammadayyoub": "https://cdn.islamic.network/quran/audio/128/ar.muhammadayyoub/5901.mp3",
    "muhammadjibreel": "https://cdn.islamic.network/quran/audio/128/ar.muhammadjibreel/5901.mp3",
    "shaatree": "https://cdn.islamic.network/quran/audio/128/ar.shaatree/5901.mp3"
  },
  "words": [
    {
      "id": 19695,
      "line_number": 11,
      "audio_url": "https://audio.qurancdn.com/wbw/084_017_001.mp3",
      "text": "وَٱلَّيْلِ",
      "translation": "dan malam",
      "transliteration": "wa-al-layli"
    },
    {
      "id": 19696,
      "line_number": 11,
      "audio_url": "https://audio.qurancdn.com/wbw/084_017_002.mp3",
      "text": "وَمَا",
      "translation": "dan apa",
      "transliteration": "wamā"
    },
    {
      "id": 19697,
      "line_number": 11,
      "audio_url": "https://audio.qurancdn.com/wbw/084_017_003.mp3",
      "text": "وَسَقَ",
      "translation": "menyelubungi",
      "transliteration": "wasaqa"
    },
    {
      "id": 19698,
      "line_number": 11,
      "audio_url": null,
      "text": "١٧",
      "translation": "(17)",
      "transliteration": null
    }
  ],
  "translation": {
    "text": "dan dengan malam dan apa yang diselubunginya,",
    "resource_name": "King Fahad Quran Complex"
  }
}